{
  "world": "62fd7584-658a-4a00-8f3f-d10a5b704eda",
  "id": "buhayra",
  "customName": "buhayra",
  "rewards": [],
  "sound": "UI.TOAST.CHALLENGE_COMPLETE",
  "icon": "TOTEM_OF_UNDYING",
  "iconModel": 0,
  "undiscoveredIconModel": 0,
  "undiscoveredIcon": "TOTEM_OF_UNDYING",
  "iconCommand": [],
  "showCoords": false,
  "location": {
    "world": "world",
    "x": 6999.433267956501,
    "y": 65.85378172799199,
    "z": -6596.750228563312,
    "pitch": 68.250015,
    "yaw": -27.90001
  },
  "hints": [],
  "showHint": false,
  "teleportable": false,
  "hidden": false,
  "discoverable": true,
  "effects": [],
  "requirements": [],
  "discoveredLore": [],
  "alwaysShowTitles": false,
  "title": null,
  "subtitle": null,
  "discoveredTitle": null,
  "discoveredSubtitle": null,
  "regenerate": null,
  "teleportCooldown": 0,
  "teleportCost": 0.0,
  "showActionbar": true,
  "opacity": 0.5,
  "lineOpacity": 0.5,
  "colour": "13369344",
  "lineColour": "13369344",
  "dynmap": true,
  "secondsInsideToDiscover": 0,
  "disablePassthrough": false
}